pmtarray/__init__.py
pmtarray/array.py
pmtarray/unit.py
pmtarray/models/R11410.py
pmtarray/models/R12699.py
pmtarray/models/__init__.py
pmtarray/models/model_lib.py
pmtarray/scripts/__init__.py
pmtarray/scripts/script_pmtarray.py
pmtarray/scripts/script_pmtunit.py
pmtarray-1.0.dist-info/licenses/LICENSE
pmtarray-1.0.dist-info/METADATA
pmtarray-1.0.dist-info/WHEEL
pmtarray-1.0.dist-info/entry_points.txt
pmtarray-1.0.dist-info/top_level.txt
pmtarray-1.0.dist-info/RECORD
