Metadata-Version: 2.4
Name: pmtarray
Version: 1.0
Summary: A simple package to get the geometry of PMT arrays.
Author-email: Ricardo Peres <rperes@physik.uzh.ch>
Project-URL: Homepage, https://github.com/ricmperes/pmtarray
Project-URL: Bug Tracker, https://github.com/ricmperes/pmtarray/issues
Project-URL: Documentation, https://ricmperes.github.io/pmtarray/
Classifier: Programming Language :: Python :: 3
Classifier: License :: OSI Approved :: BSD License
Classifier: Operating System :: OS Independent
Classifier: Development Status :: 5 - Production/Stable
Classifier: Natural Language :: English
Classifier: Topic :: Scientific/Engineering :: Physics
Requires-Python: >=3.7
License-File: LICENSE
Requires-Dist: numpy
Requires-Dist: matplotlib
Requires-Dist: hexalattice
Requires-Dist: pandas
Dynamic: license-file
